[{"authors":["admin"],"categories":null,"content":" Maritime Robotx Challengeへむけて結成された、学生主体のロボコンチームです。\nそれぞれのチームは制御機器、制御系、センサー、さらにそのアルゴリズム等を開発し、それらを WAM-Vという船体に搭載して大会に出場します。\n船は完全自動運転でなくてはならず、大会中には様々なタスクが課されます。\n  大会中の船の様子   次回大会は、2024年にアメリカ フロリダ州にて開催予定です。\n私達と一緒に『世界一かしこい自動航行船』をつくりませんか？？\n興味をもっていただけたら、 お問い合わせよりご連絡ください！！\nまた、チームではスポンサー募集を随時行っています。\n詳細に関しましては、 スポンサー募集ページをご確認ください。\n  ","date":1610196289,"expirydate":-62135596800,"kind":"taxonomy","lang":"ja","lastmod":1610196289,"objectID":"2525497d367e79493fd32b198b28f040","permalink":"https://www.ouxt.jp/author/ouxt-polaris/","publishdate":"0001-01-01T00:00:00Z","relpermalink":"/author/ouxt-polaris/","section":"authors","summary":"Maritime Robotx Challengeへむけて結成された、学生主体のロボコン","tags":null,"title":"OUXT Polaris","type":"authors"},{"authors":["KentaFutami"],"categories":null,"content":"","date":-62135596800,"expirydate":-62135596800,"kind":"taxonomy","lang":"ja","lastmod":-62135596800,"objectID":"42e3f38c3708546454fdaa91a756c791","permalink":"https://www.ouxt.jp/author/%E4%BA%8C%E8%A6%8B-%E5%A0%85%E5%A4%AA/","publishdate":"0001-01-01T00:00:00Z","relpermalink":"/author/%E4%BA%8C%E8%A6%8B-%E5%A0%85%E5%A4%AA/","section":"authors","summary":"","tags":null,"title":"二見 堅太","type":"authors"},{"authors":["KeisukeYoshida"],"categories":null,"content":"","date":-62135596800,"expirydate":-62135596800,"kind":"taxonomy","lang":"ja","lastmod":-62135596800,"objectID":"dd84b75c48faa3e95ad48d6a54c740b2","permalink":"https://www.ouxt.jp/author/%E5%90%89%E7%94%B0-%E5%9C%AD%E4%BD%91/","publishdate":"0001-01-01T00:00:00Z","relpermalink":"/author/%E5%90%89%E7%94%B0-%E5%9C%AD%E4%BD%91/","section":"authors","summary":"","tags":null,"title":"吉田 圭佑","type":"authors"},{"authors":["Masato Kobayashi"],"categories":null,"content":"プロフィール 博士(工学).\nこれまで大学、民間企業、ロボコンにて、 自律/遠隔型知能ロボット・人支援システム（移動やマニピュレーション等）に関する研究・技術開発に従事.\n   年月 所属等     2013年 4月-2017年 3月 神戸大学（マリンエンジニアリング学科、元井研究室）を卒業   2017年 4月-2019年 3月 神戸大学大学院 博士課程前期課程（マリンエンジニアリングコース、元井研究室）を修了   2019年 4月-2021年 9月 セイコーエプソン株式会社 技術開発本部でロボットや製造装置(自動化)に関する研究技術開発に従事   2019年 10月-2022年 9月 神戸大学大学院 博士課程後期課程（海事科学専攻、元井研究室）を修了.博士（工学）   2021年 11月-2022年 3月 オムロンサイニックエックス株式会社リサーチインターンに従事.Robotics×AIに関する研究   2021年 11月-2022年 9月 国立研究開発法人科学技術振興機構 (JST) 次世代研究者挑戦的研究プログラムに従事   2022年 9月-現在 OUXT Polaris メンバー:自律航行船の国際ロボットコンテストのMaritime RobotX Challengeへ向けて挑戦中の日本唯一の学生主体チーム   2022年 10月-2023年 3月 神戸大学大学院　海事科学研究科　学術研究員(助教相当)   2022年 10月-現在 東京大学松尾研究室とAI×ロボットに関する研究に従事(ロボットチーム TRAIL)   2023年 4月-現在 大阪大学 サイバーメディアセンター 情報メディア教育研究部門 ( 竹村研究室)　助教に従事       個人サイト\n   researchmap\n  ","date":-62135596800,"expirydate":-62135596800,"kind":"taxonomy","lang":"ja","lastmod":-62135596800,"objectID":"f17b0a8300f1ab93bebeec9a41f0e5c5","permalink":"https://www.ouxt.jp/author/%E5%B0%8F%E6%9E%97-%E8%81%96%E4%BA%BA/","publishdate":"0001-01-01T00:00:00Z","relpermalink":"/author/%E5%B0%8F%E6%9E%97-%E8%81%96%E4%BA%BA/","section":"authors","summary":"プロフィール 博士(工学). これまで大学、民間企業、ロボコンに","tags":null,"title":"小林 聖人","type":"authors"},{"authors":["SoutaKobayashi"],"categories":null,"content":"","date":-62135596800,"expirydate":-62135596800,"kind":"taxonomy","lang":"ja","lastmod":-62135596800,"objectID":"3a81edcd9f63c86cfce756c2184b2fd6","permalink":"https://www.ouxt.jp/author/%E5%B0%8F%E6%9E%97-%E8%81%A1%E5%A4%AA/","publishdate":"0001-01-01T00:00:00Z","relpermalink":"/author/%E5%B0%8F%E6%9E%97-%E8%81%A1%E5%A4%AA/","section":"authors","summary":"","tags":null,"title":"小林 聡太","type":"authors"},{"authors":["KentaOkamoto"],"categories":null,"content":"","date":-62135596800,"expirydate":-62135596800,"kind":"taxonomy","lang":"ja","lastmod":-62135596800,"objectID":"f1c9dcb354317091972f176b6c105901","permalink":"https://www.ouxt.jp/author/%E5%B2%A1%E6%9C%AC-%E5%81%A5%E5%A4%AA/","publishdate":"0001-01-01T00:00:00Z","relpermalink":"/author/%E5%B2%A1%E6%9C%AC-%E5%81%A5%E5%A4%AA/","section":"authors","summary":"","tags":null,"title":"岡本 健太","type":"authors"},{"authors":["KentoHirogaki"],"categories":null,"content":"","date":-62135596800,"expirydate":-62135596800,"kind":"taxonomy","lang":"ja","lastmod":-62135596800,"objectID":"75df9189da3e5ec7c73300782e74fe47","permalink":"https://www.ouxt.jp/author/%E5%BB%A3%E5%9E%A3-%E8%B3%A2%E8%B1%8A/","publishdate":"0001-01-01T00:00:00Z","relpermalink":"/author/%E5%BB%A3%E5%9E%A3-%E8%B3%A2%E8%B1%8A/","section":"authors","summary":"","tags":null,"title":"廣垣 賢豊","type":"authors"},{"authors":["FumiyaMatsuzaki"],"categories":null,"content":"プロフィール 2023.10-Present: StrayedCats (The Championship of Robotics Engineers)\n2023.04-Present: OUXT Polaris (Maritime RobotX Challenge)\n2022.10-2024.03: Hibikino-Musashi@Home (RoboCup@Home)\n2020.08-2023.03: FUKUOKA NIWAKA (RoboMaster)\n","date":-62135596800,"expirydate":-62135596800,"kind":"taxonomy","lang":"ja","lastmod":-62135596800,"objectID":"0f49168649f1422c59d5afc7547addab","permalink":"https://www.ouxt.jp/author/%E6%9D%BE%E5%B4%8E-%E5%8F%B2%E5%BC%A5/","publishdate":"0001-01-01T00:00:00Z","relpermalink":"/author/%E6%9D%BE%E5%B4%8E-%E5%8F%B2%E5%BC%A5/","section":"authors","summary":"プロフィール 2023.10-Present: StrayedCats (The Championship of Robotics Engineers) 2023.04-Present: OUXT Polaris (Maritime RobotX Challenge) 2022.10-2024.03: Hibikino-Musashi@Home (RoboCup@Home) 2020.08-2023.03: FUKUOKA NIWAKA (RoboMaster)","tags":null,"title":"松崎 史弥","type":"authors"},{"authors":["AkihisaNagata"],"categories":null,"content":"","date":-62135596800,"expirydate":-62135596800,"kind":"taxonomy","lang":"ja","lastmod":-62135596800,"objectID":"f4cbed0b7289a75736aabad3c9694306","permalink":"https://www.ouxt.jp/author/%E6%B0%B8%E7%94%B0-%E6%9A%81%E4%B9%85/","publishdate":"0001-01-01T00:00:00Z","relpermalink":"/author/%E6%B0%B8%E7%94%B0-%E6%9A%81%E4%B9%85/","section":"authors","summary":"","tags":null,"title":"永田 暁久","type":"authors"},{"authors":["MasayaKataoka"],"categories":null,"content":"","date":-62135596800,"expirydate":-62135596800,"kind":"taxonomy","lang":"ja","lastmod":-62135596800,"objectID":"38908a85b46d9d575012b0d516218ba9","permalink":"https://www.ouxt.jp/author/%E7%89%87%E5%B2%A1-%E5%A4%A7%E5%93%89/","publishdate":"0001-01-01T00:00:00Z","relpermalink":"/author/%E7%89%87%E5%B2%A1-%E5%A4%A7%E5%93%89/","section":"authors","summary":"","tags":null,"title":"片岡 大哉","type":"authors"},{"authors":["ShunyaTanaka"],"categories":null,"content":"","date":-62135596800,"expirydate":-62135596800,"kind":"taxonomy","lang":"ja","lastmod":-62135596800,"objectID":"f78ad1fba0186a787de7b2cc94701655","permalink":"https://www.ouxt.jp/author/%E7%94%B0%E4%B8%AD-%E4%BF%8A%E5%93%89/","publishdate":"0001-01-01T00:00:00Z","relpermalink":"/author/%E7%94%B0%E4%B8%AD-%E4%BF%8A%E5%93%89/","section":"authors","summary":"","tags":null,"title":"田中 俊哉","type":"authors"},{"authors":["TatsuyaSanada"],"categories":null,"content":"","date":-62135596800,"expirydate":-62135596800,"kind":"taxonomy","lang":"ja","lastmod":-62135596800,"objectID":"5f96561c1117ccae2129ad702514fbfc","permalink":"https://www.ouxt.jp/author/%E7%9C%9F%E7%94%B0-%E8%BE%B0%E5%93%89/","publishdate":"0001-01-01T00:00:00Z","relpermalink":"/author/%E7%9C%9F%E7%94%B0-%E8%BE%B0%E5%93%89/","section":"authors","summary":"","tags":null,"title":"真田 辰哉","type":"authors"},{"authors":["SakuItozono"],"categories":null,"content":"","date":-62135596800,"expirydate":-62135596800,"kind":"taxonomy","lang":"ja","lastmod":-62135596800,"objectID":"1c9209bb99bcffe9b7bf52090834855a","permalink":"https://www.ouxt.jp/author/%E7%B3%B8%E5%9C%92-%E6%9C%94/","publishdate":"0001-01-01T00:00:00Z","relpermalink":"/author/%E7%B3%B8%E5%9C%92-%E6%9C%94/","section":"authors","summary":"","tags":null,"title":"糸園 朔","type":"authors"},{"authors":["ReoFujioka"],"categories":null,"content":"","date":-62135596800,"expirydate":-62135596800,"kind":"taxonomy","lang":"ja","lastmod":-62135596800,"objectID":"fe58367e735af3e53d3a995ad2a7640e","permalink":"https://www.ouxt.jp/author/%E8%97%A4%E5%B2%A1-%E6%80%9C%E7%94%9F/","publishdate":"0001-01-01T00:00:00Z","relpermalink":"/author/%E8%97%A4%E5%B2%A1-%E6%80%9C%E7%94%9F/","section":"authors","summary":"","tags":null,"title":"藤岡 怜生","type":"authors"},{"authors":["YuseiNagao"],"categories":null,"content":"","date":-62135596800,"expirydate":-62135596800,"kind":"taxonomy","lang":"ja","lastmod":-62135596800,"objectID":"b3b26a321a97c8be7f052f68552ea436","permalink":"https://www.ouxt.jp/author/%E9%95%B7%E5%B0%BE-%E6%82%A0%E4%B8%96/","publishdate":"0001-01-01T00:00:00Z","relpermalink":"/author/%E9%95%B7%E5%B0%BE-%E6%82%A0%E4%B8%96/","section":"authors","summary":"","tags":null,"title":"長尾 悠世","type":"authors"},{"authors":["Masaya Kataoka"],"categories":null,"content":"OUXT Polarisでは開発を通して得た知見をROSコミュニティやロボット競技コミュニテイに還元するべく精力的に講演活動を行なっています。 これまでの講演内容は以下の通りです。\nRobotX Maritime RobotX Challengeの採点項目にはチームごとに提出されるTechnical Documentationの内容も含まれています。 OUXT Polarisで過去に執筆したTechnical Documentationは以下のようなものがあります。\nRobotX 2014    場所 発表日 発表者 演題     Singapore  Naoya Fujimoto, et al  Catamaran Robot “Polaris -I” for Maritime RobotX Challenge 2014    RobotX 2016    場所 発表日 発表者 演題     Hawaii  Suisei Wada, et al  Google Scholar Link    RobotX 2018    場所 発表日 発表者 演題     Hawaii 2018/12/15 堀口修平  Design Presentation    OUXT Polaris勉強会 OUXT Polarisでは月に一度程度の頻度で勉強会を開催しています。 勉強会においてはチーム外の方にも来ていただいて議論や知見の共有を行なっています。\nhttps://ouxt-polaris.connpass.com\nROSJP ROSJPは日本のROSユーザーグループです。 OUXT Polarisでは日本のROSコミュニティに情報発信するべく積極的に発表しております。 また、現在チームメンバーの片岡は2021年よりROSJPの運営チームの一員となっています。\nROS Japan UG #13 移動ロボット勉強会    場所 発表日 発表者 演題     東京 2017/10/25 片岡大哉、和田翠星  GazeboでUSV シミュレーション    https://rosjp.connpass.com/event/66253/\nROS Japan UG #18 関西勉強会    場所 発表日 発表者 演題     滋賀 2017/12/17 片岡大哉、西下敦生  pclで三次元物体認識    https://rosjp.connpass.com/event/72045/\nROS Japan UG #34 LT大会（持ち込みLT）    場所 発表日 発表者 演題     東京 2020/02/17 片岡大哉  ROS2で共有ライブラリを作るのがとてもつらいお話 動画    https://rosjp.connpass.com/event/161041/\nROS Japan UG Re: #35 自作／カスタムロボットのROS対応 Webinar    場所 発表日 発表者 演題     オンライン 2020/12/14 吉本幸太郎 自動航行船のROS2対応 動画    https://rosjp.connpass.com/event/197222/\nROS Japan UG #38 オンラインROS勉強会    場所 発表日 発表者 演題     オンライン 2020/08/28 片岡大哉 ROS2のドキュメント自動生成してみた 動画    https://rosjp.connpass.com/event/183750/\nROS Japan UG #43 組み込み勉強会    場所 発表日 発表者 演題     オンライン 2021/7/17 片岡 大哉  ros2_controlで動くロボット 多摩川で浮かべてみた    https://rosjp.connpass.com/event/215366/\nROSCON ROSCONは査読ありのROS開発者の国際会議です。 OUXT PolarisではROSCONJPの2018,2019,2021の本会議に提案が採択された実績及びROSCON MacauにてメンバーがLightning Talkを行なった実績があります。\nROSCONJP 2018    場所 発表日 発表者 演題     東京 2018/9/14 田中良道  Maritime RobotX Challenge 2018への取り組み    Abstract OUXT Polarisは日本各地の高専生・大学生・大学院生を中心に構成されたチームである。自律走行船の国際大会であるMaritime RobotX Challengeへ唯一の日本チームとして参加し、入賞することを活動目的としている。ROSCon JP 2018 においては、開発中の機体について各技術要素とROSによるシステム統合技術を紹介し、知識と経験の共有を図るとともに、要素技術に関する議論を期待している。\n video\nROSCONJP 2019    場所 発表日 発表者 演題     東京 2019/09/25 片岡大哉・和田翠星・増岡伸也・田中良道  Virtual RobotX Chellengeへ向けたオープンソース自律航行システムの開発    Abstract OUXT PolarisはMaritime RobotX Challengeに日本から有志で参加しているチームである。2018年大会ではタスクをROSを用いてOSSの自律航行システムを構築し、大会ではタスクを1つクリアした。今年は、シミュレーターによる大会Virtual RobotX Challengeが開催される。ROSCon JP 2019では、昨年の反省を踏まえたソフトウェアアーキテクチャの改良と、成果物によるROSコミュニティへの貢献について発表を行う。 video\nROSCON 2019 Macau    場所 発表日 発表者 演題     マカオ 2019/11/1 片岡大哉  pcl_appsとROS2で始める点群処理    ROSCONJP 2021    場所 発表日 発表者 演題     東京 2021/9/16 吉本幸太郎・小倉将人  Martime RobotX Challenge2022 のためのビヘイビアプランニング開発 動画　https://vimeo.com/638043225/b9f16e187d   東京 2021/9/16 片岡大哉  ros-integration-action 無料で始める簡単結合テスト    https://roscon.jp/\nAbstract OUXT-Polaris は完全自律航行船の国際コンテスト出場を目指すチームである。自律航行のためのビヘイビアプラニングには BehaviorTree.CPP ライブラリ1を使用している。 OUXT ではこのライブラリを更に便利に使うための拡張ツールを開発した。また、自動航行ソフトウェアのテストには実機実験が大切である。コロナ禍でも実施可能な OUXT-Polaris の取り組みを紹介する。\n他ロボット競技チームとの交流 ごちゃまぜロボットコンテスト交流会 #1 回路・制御セッションLT    場所 発表日 発表者 演題     オンライン 2021/8/29 真田 辰哉  回路のドキュメント， 残してますか？   オンライン 2021/8/29 片岡 大哉  コロナ禍でもみんなでできるフィールド実験を目指して    https://scramble-robocon-meetup.connpass.com/event/218937/\nフィールドロボティクス勉強会 #1    場所 発表日 発表者 演題     オンライン 2019/12/20 片岡 大哉  ソフト屋から見たフィールドロボット スコールに負けない認識系を作る！！    https://frj.connpass.com/event/156793/\nそとろぼ！ 第2回フィールドロボティクス勉強会オンライン    場所 発表日 発表者 演題     オンライン 2021/8/28 片岡 大哉  ros2_controlで動くロボット 多摩川、安威川で浮かべてみた    https://frj.connpass.com/event/219686/\n自律移動勉強会with Robohan    場所 発表日 発表者 演題     オンライン 2021/9/19 片岡 大哉  自律移動勉強会 with Robohan    その他勉強会 第12回 MLOps 勉強会    場所 発表日 発表者 演題     オンライン 2021/10/14 片岡 大哉  ロボットシステムの開発と運用、本番で一発完動するロボットシステムのために    https://mlops.connpass.com/event/223517/\nUnity Dojo　秋のLT祭り    場所 発表日 発表者 演題     オンライン 2021/10/19 片岡大哉  UniSim、ROS2に最適化されたUnityベースのシミュレータ    https://meetup.unity3d.jp/jp/events/1332\nUnityは物理エンジンや高度なレンダリングパイプラインを備え、ロボティクス分野への応用が期待されている。 Maritime RobotX Challengeに出場しているOUXT Polarisでは実機テストのコスト削減のためUnityベースでROS2に最適化されたシミュレータの開発に着手している。 今回の講演ではURDFのインポートやネイティブライブラリを利用したROS2トピックPub/Sub等の技術を紹介する。\n","date":1637297427,"expirydate":-62135596800,"kind":"page","lang":"ja","lastmod":1637297427,"objectID":"48c85f7f4353f7338fe3cf7e1ca191bc","permalink":"https://www.ouxt.jp/pages/seminar/publications/","publishdate":"2021-11-19T13:50:27+09:00","relpermalink":"/pages/seminar/publications/","section":"pages","summary":"OUXT Polarisの過去の発表実績のまとめ","tags":null,"title":"講演実績","type":"pages"},{"authors":["OUXT Polaris"],"categories":[],"content":"OUXTでは2019年までROS1を，以降はROS2を使って開発を行っています． また，普段から研究や仕事でROS/ROS2を使っているメンバーが所属しています．\nそんなOUXTのメンバーが皆さんのROS/ROS2の悩みに回答します！！\n質問内容は些細なことや抽象的なことでも大丈夫です．\n質問にはプライバシーや開発中のものに関する情報など含むので返答は収集させていただいたメールアドレスに対して返答させていただきます． また，ROS/ROS2に関する知見の共有のため，デリケートな情報を除いた上で投稿から2ヶ月以上後に質問・回答をHPに掲載させていただく場合があります．\n読み込んでいます…","date":1610196289,"expirydate":-62135596800,"kind":"page","lang":"ja","lastmod":1610196289,"objectID":"37b753550f1b0bfd5b7b22603d035377","permalink":"https://www.ouxt.jp/pages/seminar/ros_help/","publishdate":"2021-01-09T21:44:49+09:00","relpermalink":"/pages/seminar/ros_help/","section":"pages","summary":"ROSのお悩み，聞きます！","tags":[],"title":"ROS駆け込み寺","type":"pages"},{"authors":["HidetoNiwa"],"categories":["OUXT勉強会","イベント"],"content":"こんにちは！運営担当のにゎ～んこと丹羽です！\nさてタイトルの通り、OUXT-Polaris勉強会：特別編を開催します！   今回のOUXT Polaris勉強会は\u0026hellip;「特別編：ROSを使ったロボット開発講座」です！\n当チームの片岡 大哉（ @hakuturu583）が発表します！\nROSをどのようにロボットへと組み込んでいくのか？初歩から解説していきたいと思います～！\n本勉強会はチーム内の技術向上を目的として開催していますが、一般の方でも参加可能です！\n皆さまの参加をお待ちしてます～\n公式ハッシュタグは『 #OUXT勉強会』となっています。皆さまの投稿よろしくお願いします！\n特別編：ROSを使ったロボット開発講座 日時 12/20 13:00～16:00（途中休憩あり）\n発表者 片岡 大哉\nタイトル 特別編：ROSを使ったロボット開発講座\n申し込み方法  connpass イベントページよりお願いいたします。\nZoomを用いて開催します。参加者には開始1時間前までにURLを送付いたしますので、そちらの方から参加お願いします。\n","date":1606539027,"expirydate":-62135596800,"kind":"page","lang":"ja","lastmod":1606539027,"objectID":"0692956039fa6770f75d9854a6d507f4","permalink":"https://www.ouxt.jp/post/ros-seminar/","publishdate":"2020-11-28T13:50:27+09:00","relpermalink":"/post/ros-seminar/","section":"post","summary":"特別編：ROSを使ったロボット開発講座 に関して","tags":["OUXT勉強会","イベント"],"title":"特別編：ROSを使ったロボット開発講座","type":"post"},{"authors":["HidetoNiwa"],"categories":["RobotX","RobotX2020"],"content":"運営担当のにゎ～んこと丹羽です！\nさて、表題の通りOUXT Polarisが挑戦していたMaritime Robotx Challenge2020ですが、COVID-19の影響により大会開催が中止となりました。 ご支援、応援いただきました皆様、ありがとうございました。\nチームでは今回の開発経験を発表する場を大会時期に設けることを検討しています。ご期待ください！\nチームでは引き続き、Virtual RobotX Competition 2021（シミュレーション上での大会）や次大会であるMaritime Robotx Challenge2022へ挑戦していきたいと思います。\nご支援と応援の程、今後ともよろしくお願いいたします。\n","date":1599057419,"expirydate":-62135596800,"kind":"page","lang":"ja","lastmod":1599057419,"objectID":"91ebc49ca63799d49d399d4aa5184546","permalink":"https://www.ouxt.jp/post/robotx2020-cancelled/","publishdate":"2020-09-02T23:36:59+09:00","relpermalink":"/post/robotx2020-cancelled/","section":"post","summary":"RobotX2020 開催中止に関して","tags":["RobotX","RobotX2020"],"title":"RobotX2020 開催中止に関して","type":"post"},{"authors":["HidetoNiwa"],"categories":["イベント情報","OUXT勉強会"],"content":"こんにちは！運営担当のにゎ～んこと丹羽です！\nさてタイトルの通り、第4回OUXT-Polaris勉強会を開催します！   今回は『海外チーム技術解説 その１：エンブリーリドル航空大学』です！回路班の西下が\n初の海外チームの技術書の開設となっています！他チームにてどのような開発が行われているのかの紹介です！\n本勉強会はチーム内の技術向上を目的として開催していますが、一般の方でも参加可能です！\n皆さまの参加をお待ちしてます～\n公式ハッシュタグは『 #OUXT勉強会』となっています。皆さまの投稿よろしくお願いします！\n第4回OUXT-Polaris勉強会 日時 7/15 22:00～23:00\n発表者 西下 敦青\nタイトル 海外チーム技術解説 その１：エンブリーリドル航空大学\n申し込み方法  connpass イベントページよりお願いいたします。\nZoomを用いて開催します。参加者には開始1時間前までにURLを送付いたしますので、そちらの方から参加お願いします。\n","date":1593873419,"expirydate":-62135596800,"kind":"page","lang":"ja","lastmod":1593873419,"objectID":"ab6870c6f56b038ea3e37e3be7f83ee1","permalink":"https://www.ouxt.jp/post/4-seminar/","publishdate":"2020-07-04T23:36:59+09:00","relpermalink":"/post/4-seminar/","section":"post","summary":"第4回 OUXT-Polaris勉強会 開催のお知らせ","tags":["イベント情報","OUXT勉強会"],"title":"第4回 OUXT-Polaris勉強会 開催！","type":"post"},{"authors":["OUXT Polaris"],"categories":[],"content":"OUXT Polarisではロボット製作/開発費、ロボット輸送費を必要としています。\nそのため、スポンサーを随時募集しています。\nご不明な点がございましたら、 お問い合わせよりご連絡お願いします。\n金銭支援スポンサー 私たちOUXT Polarisでは、ロボットのパーツや輸送費にお金を必要としています。\nそれらの支援をしていただけるスポンサー様を募集しています。\n物的支援スポンサー 私たちOUXT-Polarisでは、様々な製品を用いて完全に自律制御された船の開発を行っています。\n貴社の名前のタグをつけた貴社製品を用いたブログの記載などを行います。\n貴社の製品をお貸しいただきましたら、半額を協賛金とさせていただきます。\nもしこれらに興味を持っていただけましたら、 お問い合わせ よりご連絡お願いします。\nGold Sponsors 対象：￥1,000,000以上\nあなたの会社のロゴを下記に掲載させていただきます！\n 船体  Webサイト（スポンサーページ） チームユニホーム オープンソースのシミュレーション上の船の3Dモデル上 私たちのGitHubのすべてのREADME.mdファイル上  Silver Sponsors 対象：￥500,000以上\nあなたの会社のロゴを下記に掲載させていただきます！\n 船体  Webサイト（スポンサーページ） チームユニホーム  Bronze Sponsors 対象：￥300,000以上\nあなたの会社のロゴを下記に掲載させていただきます！\n 船体  Webサイト（スポンサーページ） チームユニホーム  ","date":1592969663,"expirydate":-62135596800,"kind":"page","lang":"ja","lastmod":1592969663,"objectID":"b88f5cb84ca7da7ef9326c1d911fe247","permalink":"https://www.ouxt.jp/pages/call-sponsor/","publishdate":"2020-06-24T12:34:23+09:00","relpermalink":"/pages/call-sponsor/","section":"pages","summary":"私たちのチームではスポンサーを募集しています。","tags":[],"title":"スポンサー募集","type":"pages"},{"authors":["HidetoNiwa"],"categories":["イベント情報","OUXT勉強会"],"content":"こんにちは！運営担当のにゎ～んこと丹羽です！\nさてタイトルの通り、第3回OUXT-Polaris勉強会を開催します！   今回は『RobotX2020に向けたハードウェアデザインレビュー』です！ハード班の真田が\nハードウェア系（＋電気系）でこんなやつを作ろうとしているので、おかしなところがあったら教えて下さい！\nといった感じだそうです。OUXT-Polaris勉強会初のハードウェア系のお話です！\n本勉強会はチーム内の技術向上を目的として開催していますが、一般の方でも参加可能です！\n皆さまの参加をお待ちしてます～\n公式ハッシュタグは『 #OUXT勉強会』となっています。皆さまの投稿よろしくお願いします！\n第3回OUXT-Polaris勉強会 日時 7/1 22:00～23:00\n発表者 真田 辰哉\nタイトル RobotX2020に向けたハードウェアデザインレビュー\n申し込み方法  connpass イベントページよりお願いいたします。\nZoomを用いて開催します。参加者には開始1時間前までにURLを送付いたしますので、そちらの方から参加お願いします。\n","date":1592923019,"expirydate":-62135596800,"kind":"page","lang":"ja","lastmod":1592923019,"objectID":"0ec7a4c0e6fc811ca391a603d57c3bc1","permalink":"https://www.ouxt.jp/post/3-seminar/","publishdate":"2020-06-23T23:36:59+09:00","relpermalink":"/post/3-seminar/","section":"post","summary":"第3回 OUXT-Polaris勉強会 開催のお知らせ","tags":["イベント情報","OUXT勉強会"],"title":"第3回 OUXT-Polaris勉強会 開催！","type":"post"},{"authors":["HidetoNiwa"],"categories":["イベント情報","OUXT勉強会"],"content":"こんにちは！運営担当のにゎ～んこと丹羽です！\nさてタイトルの通り、第2回OUXT-Polaris勉強会を開催します！   今回は「RobotXに向けたビヘイビアツリーによる自動航行船の行動計画」です！制御班の吉本くんがROS2を用いたビヘイビアツリーによる行動計画のお話をしてくれます～\n前回の勉強会に引き続き、ROS2のお話です！\n本勉強会はチーム内の技術向上を目的として開催していますが、一般の方でも参加可能です！\n皆さまの参加をお待ちしてます！\n公式ハッシュタグは『 #OUXT勉強会』です～\nぜひぜひつぶやいてみてください～\n第2回OUXT-Polaris勉強会 日時 6/17 22:00～23:00\n発表者 吉本 幸太郎\nタイトル RobotXに向けたビヘイビアツリーによる自動航行船の行動計画\n申し込み方法  connpass イベントページよりお願いいたします。\nZoomを用いて開催します。参加者には開始1時間前をめどにURLを送付いたしますので、そちらの方から参加お願いします。\n","date":1591627019,"expirydate":-62135596800,"kind":"page","lang":"ja","lastmod":1591627019,"objectID":"198b9ca2b27f2af24d1684fbd48e2794","permalink":"https://www.ouxt.jp/post/2-seminar/","publishdate":"2020-06-08T23:36:59+09:00","relpermalink":"/post/2-seminar/","section":"post","summary":"第2回 OUXT-Polaris勉強会 開催のお知らせ","tags":["イベント情報","OUXT勉強会"],"title":"第2回 OUXT-Polaris勉強会 開催！","type":"post"},{"authors":["HidetoNiwa"],"categories":["イベント情報","OUXT勉強会"],"content":"こんにちは！運営担当のにゎ～んこと丹羽です！\nさてタイトルの通り、OUXT-Polaris主催の勉強会を開催します！   OUXT所属のメンバーがロボティクス関連の話題を発表していきます。\n隔週水曜日 22時～23時に開催する予定です。\nまた、これに合わせまして 勉強会ページを開設しました！\n今後こちらの方に、勉強会日程/発表者/テーマ等の更新を行って行きますのでよろしくお願いいたします～\n第1回勉強会 日時 6/3 22:00～23:00\n発表者 片岡 大哉\nタイトル RobotXに向けたプランナーの開発\n申し込み方法  connpass イベントページよりお願いいたします。\nZoomを用いて開催します。参加者には開始1時間前をめどにURLを送付いたしますので、そちらの方から参加お願いします。\n","date":1590763019,"expirydate":-62135596800,"kind":"page","lang":"ja","lastmod":1590763019,"objectID":"88118380e5d4c771d0baafa2c43d3a75","permalink":"https://www.ouxt.jp/post/1-seminar/","publishdate":"2020-05-29T23:36:59+09:00","relpermalink":"/post/1-seminar/","section":"post","summary":"第1回 OUXT-Polaris勉強会 開催のお知らせ","tags":["イベント情報","OUXT勉強会"],"title":"第1回 OUXT-Polaris勉強会 開催！","type":"post"},{"authors":[],"categories":[],"content":"   概要 OUXT-Polarisではzoomを用いた、オンライン勉強会を開催しています。\nOUXTのメンバーだけでなく、一般の方の参加も大歓迎です。\nロボティクス関連の話題をOUXTメンバーが発表します。\n申し込み方法 connpassより前日23時30分までに申し込みください。\n（各回のリンクは下記にあります。）\n発表テーマ 開催前の回に関しましては内容が変更となる場合がございます。ご容赦ください。\nまた、空白欄となっているところは未定となっておりますのでご注意ください。\n    日時 発表者 タイトル 申し込みページ     第1回 6/3 22:00～23:00 片岡 大哉 RobotXに向けたプランナーの開発 開催終了   第2回 6/21 22:00～23:00 吉本 幸太郎 RobotXに向けたビヘイビアツリーによる\n自動航行船の行動計画 開催終了   第3回 7/1 22:00～23:00 真田 辰哉 RobotX2020に向けたハードウェアデザインレビュー 開催終了   第4回 7/15 22:00～23:00 西下 敦青 海外チーム技術解説 その１：エンブリーリドル航空大学 参加者募集中   第5回 7/29 22:00～23:00       ","date":1590727751,"expirydate":-62135596800,"kind":"page","lang":"ja","lastmod":1590727751,"objectID":"164ef1dcc67e71166f512e2b52f5f04e","permalink":"https://www.ouxt.jp/pages/seminar/seminar/","publishdate":"2020-05-29T13:49:11+09:00","relpermalink":"/pages/seminar/seminar/","section":"pages","summary":"OUXTで開催している勉強会に関して","tags":["OUXT勉強会"],"title":"OUXT-Polaris 勉強会","type":"pages"},{"authors":["HidetoNiwa"],"categories":[],"content":"こんにちは！運営担当のにゎ～んです！\nさて、OUXTではRobotX2020に向けての決起会をオンラインでzoomを用いて行いました～！\n本来であれば大阪府立大学にて、ロボットを囲んで活動を行いたいのですが、COVID-19の影響もありオンラインでのミートアップ会となりました。\n各メンバーのRobotXに対する挑戦的な思いが感じられるよい会となりました～！   RobotX2020 オンライン決起会の様子   また、HPの方も従来のものから新しい本サイトへと一新しました。\n本年度は決勝進出を目標として挑戦していきます！応援のほどよろしくお願いいたします。\n","date":1590189803,"expirydate":-62135596800,"kind":"page","lang":"ja","lastmod":1590189803,"objectID":"69db148e384bd70a82bbcf4ad25be51c","permalink":"https://www.ouxt.jp/post/1-startup2020/","publishdate":"2020-05-23T08:23:23+09:00","relpermalink":"/post/1-startup2020/","section":"post","summary":"こんにちは！運営担当のにゎ～んです！ さて、OUXTではRob","tags":["RobotX2020"],"title":"RobotX2020 オンライン決起会開催！","type":"post"}]